image_processing_01/__init__.py
image_processing_01/processing/__init__.py
image_processing_01/processing/combination.py
image_processing_01/processing/transformation.py
image_processing_01/utils/__init__.py
image_processing_01/utils/io.py
image_processing_01/utils/plot.py
package_name_1-0.0.1.dist-info/METADATA
package_name_1-0.0.1.dist-info/WHEEL
package_name_1-0.0.1.dist-info/top_level.txt
package_name_1-0.0.1.dist-info/RECORD
