Metadata-Version: 2.1
Name: package-name-1
Version: 0.0.1
Summary: Desafio criação de pacotes
Home-page: https://github.com/rafaelsom
Author: Rafael
Author-email: rafaelsomr1@gmail.com
License: UNKNOWN
Platform: UNKNOWN
Requires-Python: >=3.8
Requires-Dist: matplotlib
Requires-Dist: numpy
Requires-Dist: scikit-image (>=0.16.1)
